alak/__init__.py
alak/alak_grammar.py
alak/cli.py
alak/interpreter.py
alak-0.1.2.dist-info/METADATA
alak-0.1.2.dist-info/WHEEL
alak-0.1.2.dist-info/entry_points.txt
alak-0.1.2.dist-info/top_level.txt
alak-0.1.2.dist-info/RECORD
