Metadata-Version: 2.4
Name: alak
Version: 0.1.2
Summary: A Filipino-flavored programming language.
Author: leetz-kowd
Author-email: Jino Lacson <jino@example.com>
License: MIT
Requires-Python: >=3.8
Requires-Dist: lark>=1.1.7
Dynamic: author
